{
  "stationId": "10637",
  "forecast1": {
    "stationId": "10637",
    "start": 1782943200000,
    "timeStep": 3600000,
    "temperature": [
      189,
      173,
      161,
      149,
      142,
      140,
      145,
      161,
      182,
      204,
      226,
      242,
      256,
      267,
      276,
      281,
      282,
      280,
      274,
      262,
      250,
      238,
      225,
      211,
      199,
      187,
      175,
      165,
      154,
      145,
      145,
      153,
      169,
      181,
      195,
      206,
      215,
      224,
      234,
      243,
      249,
      253,
      253,
      251,
      240,
      226,
      209,
      193,
      177,
      165,
      153,
      143,
      134,
      128,
      129,
      143,
      164,
      182,
      202,
      219,
      232,
      242,
      256,
      265,
      274,
      280,
      277,
      276,
      266,
      250,
      233,
      217,
      203,
      193,
      185,
      179,
      172,
      170,
      171,
      181,
      193,
      207,
      220,
      231,
      235,
      244,
      249,
      259,
      262,
      265,
      263,
      256,
      248,
      236,
      224,
      208,
      199,
      190,
      181,
      173,
      168,
      166,
      167,
      175,
      185,
      199,
      210,
      223,
      232,
      242,
      250,
      256,
      256,
      255,
      250,
      245,
      237,
      228,
      215,
      203,
      194,
      186,
      179,
      173,
      166,
      164,
      165,
      172,
      184,
      194,
      205,
      213,
      221,
      227,
      234,
      239,
      241,
      237,
      232,
      226,
      218,
      208,
      198,
      187,
      178,
      170,
      162,
      156,
      151,
      147,
      147,
      156,
      165,
      177,
      186,
      195,
      204,
      210,
      215,
      220,
      225,
      226,
      225,
      222,
      219,
      208,
      196,
      185,
      177,
      170,
      162,
      154,
      150,
      148,
      150,
      158,
      173,
      185,
      199,
      209,
      222,
      224,
      240,
      244,
      248,
      250,
      251,
      247,
      231,
      220,
      210,
      199,
      187,
      178,
      171,
      165,
      166,
      158,
      160,
      167,
      183,
      197,
      210,
      222,
      235,
      245,
      255,
      261,
      267,
      267,
      265,
      259,
      246,
      237,
      222,
      208,
      196,
      187,
      175,
      168,
      164,
      160,
      161,
      169,
      183,
      195,
      209,
      223,
      236,
      245,
      256,
      262,
      266,
      267,
      265,
      267,
      257,
      244,
      227,
      212,
      201
    ],
    "windSpeed": null,
    "windDirection": null,
    "windGust": null,
    "precipitationTotal": [
      0,
      0,
      0,
      0,
      0,
      0,
      0,
      0,
      0,
      0,
      0,
      0,
      0,
      0,
      0,
      0,
      0,
      0,
      0,
      0,
      0,
      0,
      0,
      0,
      0,
      0,
      0,
      0,
      0,
      0,
      0,
      0,
      0,
      0,
      0,
      0,
      0,
      0,
      0,
      0,
      0,
      0,
      0,
      0,
      0,
      0,
      0,
      0,
      0,
      0,
      0,
      0,
      0,
      0,
      0,
      0,
      0,
      0,
      0,
      0,
      0,
      0,
      0,
      0,
      0,
      0,
      0,
      0,
      0,
      0,
      0,
      0
    ],
    "sunshine": [
      0,
      0,
      0,
      0,
      0,
      0,
      0,
      180,
      350,
      490,
      540,
      530,
      510,
      510,
      470,
      420,
      400,
      380,
      330,
      310,
      270,
      220,
      170,
      90,
      0,
      0,
      0,
      0,
      0,
      0,
      0,
      180,
      350,
      480,
      530,
      530,
      500,
      470,
      430,
      420,
      420,
      450,
      460,
      480,
      460,
      440,
      330,
      180,
      0,
      0,
      0,
      0,
      0,
      0,
      0,
      170,
      350,
      510,
      600,
      590,
      590,
      540,
      560,
      560,
      550,
      510,
      520,
      490,
      460,
      380,
      250,
      130,
      0,
      0
    ],
    "dewPoint2m": [
      111,
      113,
      113,
      113,
      113,
      115,
      116,
      119,
      120,
      118,
      115,
      110,
      107,
      104,
      101,
      104,
      106,
      113,
      123,
      127,
      131,
      131,
      129,
      126,
      122,
      118,
      114,
      111,
      108,
      106,
      106,
      104,
      101,
      93,
      85,
      76,
      69,
      64,
      61,
      59,
      56,
      55,
      56,
      61,
      65,
      70,
      77,
      80,
      83,
      82,
      82,
      83,
      85,
      86,
      87,
      91,
      89,
      88,
      84,
      79,
      76,
      73,
      72,
      71,
      71,
      73,
      76,
      84,
      89,
      95,
      99,
      103
    ],
    "surfacePressure": [
      10221,
      10223,
      10221,
      10221,
      10220,
      10220,
      10222,
      10222,
      10221,
      10218,
      10215,
      10209,
      10203,
      10197,
      10191,
      10188,
      10186,
      10188,
      10192,
      10196,
      10203,
      10211,
      10217,
      10227,
      10232,
      10238,
      10243,
      10247,
      10251,
      10256,
      10259,
      10262,
      10266,
      10266,
      10266,
      10264,
      10262,
      10261,
      10258,
      10255,
      10252,
      10248,
      10250,
      10251,
      10253,
      10258,
      10261,
      10266,
      10270,
      10272,
      10273,
      10275,
      10277,
      10278,
      10280,
      10280,
      10280,
      10277,
      10274,
      10268,
      10263,
      10255,
      10248,
      10242,
      10235,
      10230,
      10227,
      10226,
      10226,
      10228,
      10232,
      10233
    ],
    "humidity": [
      669,
      732,
      791,
      827,
      838,
      822,
      747,
      667,
      585,
      505,
      450,
      400,
      368,
      342,
      325,
      330,
      338,
      367,
      421,
      464,
      512,
      553,
      595,
      628,
      659,
      692,
      718,
      755,
      785,
      774,
      735,
      655,
      596,
      517,
      458,
      407,
      368,
      334,
      310,
      295,
      282,
      280,
      286,
      316,
      353,
      406,
      470,
      530,
      584,
      626,
      668,
      713,
      751,
      751,
      691,
      620,
      546,
      479,
      420,
      375,
      346,
      312,
      294,
      277,
      267,
      276,
      283,
      317,
      360,
      415,
      470,
      526
    ],
    "isDay": [
      false,
      false,
      false,
      false,
      false,
      true,
      true,
      true,
      true,
      true,
      true,
      true,
      true,
      true,
      true,
      true,
      true,
      true,
      true,
      true,
      true,
      true,
      false,
      false,
      false,
      false,
      false,
      false,
      false,
      true,
      true,
      true,
      true,
      true,
      true,
      true,
      true,
      true,
      true,
      true,
      true,
      true,
      true,
      true,
      true,
      true,
      false,
      false,
      false,
      false,
      false,
      false,
      false,
      true,
      true,
      true,
      true,
      true,
      true,
      true,
      true,
      true,
      true,
      true,
      true,
      true,
      true,
      true,
      true,
      true,
      false,
      false
    ],
    "cloudCoverTotal": [],
    "temperatureStd": [
      0,
      14,
      15,
      16,
      15,
      15,
      17,
      14,
      11,
      10,
      10,
      10,
      10,
      10,
      9,
      11,
      11,
      11,
      12,
      12,
      12,
      12,
      12,
      13,
      13,
      12,
      13,
      15,
      15,
      15,
      16,
      14,
      12,
      11,
      11,
      11,
      11,
      11,
      9,
      9,
      9,
      9,
      10,
      11,
      9,
      10,
      11,
      12,
      13,
      14,
      15,
      15,
      16,
      17,
      18,
      15,
      13,
      12,
      12,
      12,
      12,
      11,
      12,
      12,
      12,
      13,
      14,
      15,
      14,
      15,
      15,
      16,
      16,
      15,
      15,
      15,
      15,
      16,
      16,
      14,
      13,
      14,
      15,
      16,
      17,
      17,
      17,
      17,
      16,
      16,
      16,
      16,
      16,
      16,
      16,
      15,
      15,
      15,
      16,
      16,
      17,
      18,
      18,
      16,
      14,
      15,
      18,
      19,
      19,
      20,
      20,
      21,
      22,
      22,
      22,
      22,
      21,
      20,
      19,
      19,
      17,
      17,
      18,
      18,
      19,
      18,
      17,
      16,
      15,
      16,
      19,
      20,
      23,
      20,
      22,
      23,
      23,
      23,
      24,
      23,
      22,
      20,
      21,
      19,
      20,
      22,
      21,
      22,
      23,
      22,
      22,
      21,
      20,
      18,
      18,
      18,
      19,
      19,
      20,
      20,
      20,
      21,
      21,
      21,
      21,
      20,
      20,
      19,
      20,
      19,
      19,
      19,
      19,
      19,
      20,
      17,
      16,
      18,
      18,
      19,
      20,
      20,
      21,
      21,
      20,
      20,
      21,
      22,
      21,
      20,
      20,
      19,
      19,
      19,
      20,
      19,
      20,
      20,
      19,
      18,
      17,
      17,
      17,
      18,
      20,
      20,
      22,
      22,
      22,
      23,
      22,
      22,
      22,
      20,
      20,
      19,
      18,
      18,
      19,
      19,
      19,
      19,
      20,
      17,
      17,
      18,
      20,
      22,
      23,
      22,
      23,
      23,
      24,
      24,
      25,
      24,
      24,
      23,
      22,
      21,
      20
    ],
    "icon": [
      1,
      1,
      1,
      1,
      1,
      1,
      1,
      1,
      1,
      1,
      1,
      2,
      2,
      2,
      2,
      2,
      2,
      3,
      3,
      3,
      3,
      3,
      2,
      2,
      2,
      2,
      2,
      1,
      1,
      1,
      1,
      1,
      1,
      2,
      2,
      2,
      2,
      2,
      2,
      2,
      2,
      2,
      2,
      2,
      2,
      2,
      2,
      2,
      2,
      2,
      1,
      1,
      1,
      1,
      1,
      1,
      1,
      1,
      1,
      2,
      2,
      2,
      2,
      2,
      2,
      2,
      2,
      2,
      2,
      2,
      2,
      2
    ],
    "icon1h": [
      1,
      1,
      1,
      1,
      1,
      1,
      1,
      1,
      1,
      1,
      1,
      2,
      2,
      2,
      2,
      2,
      2,
      3,
      3,
      3,
      3,
      3,
      2,
      2,
      2,
      2,
      2,
      1,
      1,
      1,
      1,
      1,
      1,
      2,
      2,
      2,
      2,
      2,
      2,
      2,
      2,
      2,
      2,
      2,
      2,
      2,
      2,
      2,
      2,
      2,
      1,
      1,
      1,
      1,
      1,
      1,
      1,
      1,
      1,
      2,
      2,
      2,
      2,
      2,
      2,
      2,
      2,
      2,
      2,
      2,
      2,
      2
    ],
    "precipitationProbablity": null,
    "precipitationProbablityIndex": null
  },
  "forecast2": {
    "stationId": "10637",
    "start": 1783202400000,
    "timeStep": 10800000,
    "temperature": [],
    "windSpeed": null,
    "windDirection": null,
    "windGust": null,
    "precipitationTotal": [
      0,
      0,
      0,
      0,
      0,
      0,
      0,
      0,
      0,
      0,
      0,
      0,
      0,
      0,
      0,
      0,
      0,
      0,
      0,
      0,
      0,
      0,
      0,
      0,
      0,
      0,
      0,
      0,
      0,
      0,
      0,
      0,
      0,
      0,
      0,
      0,
      0,
      0,
      0,
      0,
      0,
      0,
      0,
      0,
      0,
      0,
      0,
      0,
      0,
      0,
      0,
      0,
      0,
      0,
      0,
      0
    ],
    "sunshine": [
      0,
      50,
      570,
      780,
      740,
      880,
      670,
      80,
      0,
      30,
      400,
      630,
      620,
      660,
      440,
      50,
      0,
      60,
      540,
      700,
      560,
      520,
      410,
      50,
      0,
      60,
      540,
      740,
      780,
      750,
      680,
      90,
      0,
      70,
      730,
      1050,
      1040,
      1020,
      830,
      110,
      0,
      80,
      770,
      1140,
      1210,
      1100,
      810,
      100,
      0,
      90,
      870,
      1320,
      1280,
      1200,
      920,
      100
    ],
    "dewPoint2m": [
      112,
      116,
      123,
      118,
      118,
      114,
      121,
      128,
      131,
      134,
      136,
      128,
      126,
      126,
      130,
      132,
      130,
      133,
      130,
      117,
      114,
      115,
      124,
      128,
      122,
      121,
      118,
      106,
      99,
      98,
      109,
      123,
      121,
      120,
      121,
      108,
      100,
      96,
      103,
      118,
      120,
      124,
      124,
      126,
      122,
      121,
      126,
      133,
      133,
      132,
      135,
      128,
      119,
      123,
      131,
      137
    ],
    "surfacePressure": [
      10232,
      10229,
      10227,
      10218,
      10205,
      10197,
      10200,
      10205,
      10203,
      10198,
      10194,
      10189,
      10178,
      10173,
      10178,
      10181,
      10181,
      10180,
      10177,
      10172,
      10167,
      10161,
      10164,
      10173,
      10175,
      10178,
      10181,
      10173,
      10169,
      10165,
      10172,
      10179,
      10181,
      10182,
      10184,
      10178,
      10170,
      10157,
      10157,
      10166,
      10163,
      10163,
      10162,
      10154,
      10147,
      10140,
      10143,
      10151,
      10153,
      10155,
      10161,
      10156,
      10147,
      10138,
      10144,
      10154
    ],
    "humidity": [
      649,
      701,
      586,
      478,
      414,
      394,
      485,
      636,
      764,
      809,
      670,
      520,
      445,
      461,
      540,
      674,
      759,
      814,
      665,
      517,
      455,
      477,
      586,
      726,
      802,
      844,
      684,
      534,
      462,
      445,
      531,
      707,
      807,
      823,
      663,
      484,
      402,
      375,
      474,
      642,
      747,
      792,
      628,
      504,
      420,
      408,
      498,
      670,
      798,
      829,
      683,
      508,
      410,
      413,
      493,
      667
    ],
    "isDay": [
      false,
      false,
      true,
      true,
      true,
      true,
      true,
      false,
      false,
      false,
      true,
      true,
      true,
      true,
      true,
      false,
      false,
      false,
      true,
      true,
      true,
      true,
      true,
      false,
      false,
      false,
      true,
      true,
      true,
      true,
      true,
      false,
      false,
      false,
      true,
      true,
      true,
      true,
      true,
      false,
      false,
      false,
      true,
      true,
      true,
      true,
      true,
      false,
      false,
      false,
      true,
      true,
      true,
      true,
      true,
      false
    ],
    "cloudCoverTotal": [],
    "temperatureStd": [],
    "icon": [
      2,
      3,
      3,
      3,
      3,
      3,
      3,
      3,
      3,
      4,
      4,
      4,
      4,
      4,
      4,
      4,
      4,
      4,
      4,
      4,
      4,
      3,
      4,
      3,
      4,
      4,
      4,
      4,
      4,
      3,
      3,
      3,
      3,
      2,
      3,
      2,
      2,
      3,
      2,
      2,
      2,
      2,
      2,
      2,
      2,
      2,
      2,
      2,
      2,
      2,
      2,
      2,
      2,
      2,
      2,
      2
    ],
    "icon1h": [
      2,
      3,
      3,
      3,
      3,
      3,
      3,
      3,
      3,
      4,
      4,
      4,
      4,
      4,
      4,
      4,
      4,
      4,
      4,
      4,
      4,
      3,
      4,
      3,
      4,
      4,
      4,
      4,
      4,
      3,
      3,
      3,
      3,
      2,
      3,
      2,
      2,
      3,
      2,
      2,
      2,
      2,
      2,
      2,
      2,
      2,
      2,
      2,
      2,
      2,
      2,
      2,
      2,
      2,
      2,
      2
    ],
    "precipitationProbablity": null,
    "precipitationProbablityIndex": null
  },
  "days": [
    {
      "stationId": null,
      "dayDate": "2026-07-02",
      "temperatureMin": 140,
      "temperatureMax": 282,
      "precipitation": 0,
      "windSpeed": 222,
      "windGust": 500,
      "windDirection": 2400,
      "sunshine": 6170,
      "sunrise": 1782962471000,
      "sunset": 1783021097000,
      "moonrise": 1783027203000,
      "moonset": 1782969917000,
      "moonriseOnThisDay": 1783027203000,
      "moonsetOnThisDay": 1782969917000,
      "sunriseOnThisDay": 1782962471000,
      "sunsetOnThisDay": 1783021097000,
      "moonPhase": 4,
      "icon": 2,
      "icon1": null,
      "icon2": null
    },
    {
      "stationId": null,
      "dayDate": "2026-07-03",
      "temperatureMin": 145,
      "temperatureMax": 253,
      "precipitation": 0,
      "windSpeed": 148,
      "windGust": 408,
      "windDirection": 3030,
      "sunshine": 7110,
      "sunrise": 1783048913000,
      "sunset": 1783107475000,
      "moonrise": 1783114597000,
      "moonset": 1783060714000,
      "moonriseOnThisDay": 1783114597000,
      "moonsetOnThisDay": 1783060714000,
      "sunriseOnThisDay": 1783048913000,
      "sunsetOnThisDay": 1783107475000,
      "moonPhase": 4,
      "icon": 2,
      "icon1": null,
      "icon2": null
    },
    {
      "stationId": null,
      "dayDate": "2026-07-04",
      "temperatureMin": 128,
      "temperatureMax": 280,
      "precipitation": 0,
      "windSpeed": 148,
      "windGust": 426,
      "windDirection": 2620,
      "sunshine": 7760,
      "sunrise": 1783135358000,
      "sunset": 1783193850000,
      "moonrise": 1783201841000,
      "moonset": 1783151506000,
      "moonriseOnThisDay": 1783201841000,
      "moonsetOnThisDay": 1783151506000,
      "sunriseOnThisDay": 1783135358000,
      "sunsetOnThisDay": 1783193850000,
      "moonPhase": 5,
      "icon": 2,
      "icon1": null,
      "icon2": null
    },
    {
      "stationId": null,
      "dayDate": "2026-07-05",
      "temperatureMin": 170,
      "temperatureMax": 265,
      "precipitation": 0,
      "windSpeed": 204,
      "windGust": 463,
      "windDirection": 2760,
      "sunshine": 3770,
      "sunrise": 1783221805000,
      "sunset": 1783280223000,
      "moonrise": 1783289017000,
      "moonset": 1783242295000,
      "moonriseOnThisDay": 1783289017000,
      "moonsetOnThisDay": 1783242295000,
      "sunriseOnThisDay": 1783221805000,
      "sunsetOnThisDay": 1783280223000,
      "moonPhase": 5,
      "icon": 3,
      "icon1": null,
      "icon2": null
    },
    {
      "stationId": null,
      "dayDate": "2026-07-06",
      "temperatureMin": 166,
      "temperatureMax": 256,
      "precipitation": 0,
      "windSpeed": 204,
      "windGust": 482,
      "windDirection": 2630,
      "sunshine": 2830,
      "sunrise": 1783308254000,
      "sunset": 1783366593000,
      "moonrise": 1783376205000,
      "moonset": 1783333147000,
      "moonriseOnThisDay": 1783376205000,
      "moonsetOnThisDay": 1783333147000,
      "sunriseOnThisDay": 1783308254000,
      "sunsetOnThisDay": 1783366593000,
      "moonPhase": 5,
      "icon": 4,
      "icon1": null,
      "icon2": null
    },
    {
      "stationId": null,
      "dayDate": "2026-07-07",
      "temperatureMin": 164,
      "temperatureMax": 241,
      "precipitation": 0,
      "windSpeed": 167,
      "windGust": 445,
      "windDirection": 2780,
      "sunshine": 2840,
      "sunrise": 1783394706000,
      "sunset": 1783452959000,
      "moonrise": 1783463471000,
      "moonset": 1783424136000,
      "moonriseOnThisDay": 1783463471000,
      "moonsetOnThisDay": 1783424136000,
      "sunriseOnThisDay": 1783394706000,
      "sunsetOnThisDay": 1783452959000,
      "moonPhase": 5,
      "icon": 4,
      "icon1": null,
      "icon2": null
    },
    {
      "stationId": null,
      "dayDate": "2026-07-08",
      "temperatureMin": 147,
      "temperatureMax": 226,
      "precipitation": 0,
      "windSpeed": 130,
      "windGust": 370,
      "windDirection": 2790,
      "sunshine": 3640,
      "sunrise": 1783481159000,
      "sunset": 1783539324000,
      "moonrise": 1783550908000,
      "moonset": 1783515345000,
      "moonriseOnThisDay": 1783550908000,
      "moonsetOnThisDay": 1783515345000,
      "sunriseOnThisDay": 1783481159000,
      "sunsetOnThisDay": 1783539324000,
      "moonPhase": 6,
      "icon": 4,
      "icon1": null,
      "icon2": null
    },
    {
      "stationId": null,
      "dayDate": "2026-07-09",
      "temperatureMin": 148,
      "temperatureMax": 251,
      "precipitation": 0,
      "windSpeed": 130,
      "windGust": 389,
      "windDirection": 2950,
      "sunshine": 4850,
      "sunrise": 1783567614000,
      "sunset": 1783625685000,
      "moonrise": 1783638666000,
      "moonset": 1783606838000,
      "moonriseOnThisDay": 1783638666000,
      "moonsetOnThisDay": 1783606838000,
      "sunriseOnThisDay": 1783567614000,
      "sunsetOnThisDay": 1783625685000,
      "moonPhase": 6,
      "icon": 2,
      "icon1": null,
      "icon2": null
    },
    {
      "stationId": null,
      "dayDate": "2026-07-10",
      "temperatureMin": 158,
      "temperatureMax": 267,
      "precipitation": 0,
      "windSpeed": 130,
      "windGust": 389,
      "windDirection": 2520,
      "sunshine": 5210,
      "sunrise": 1783654071000,
      "sunset": 1783712043000,
      "moonrise": 1783726987000,
      "moonset": 1783698506000,
      "moonriseOnThisDay": 1783726987000,
      "moonsetOnThisDay": 1783698506000,
      "sunriseOnThisDay": 1783654071000,
      "sunsetOnThisDay": 1783712043000,
      "moonPhase": 6,
      "icon": 2,
      "icon1": null,
      "icon2": null
    },
    {
      "stationId": null,
      "dayDate": "2026-07-11",
      "temperatureMin": 160,
      "temperatureMax": 267,
      "precipitation": 0,
      "windSpeed": 148,
      "windGust": 389,
      "windDirection": 2380,
      "sunshine": 5780,
      "sunrise": 1783740531000,
      "sunset": 1783798399000,
      "moonrise": 1783816177000,
      "moonset": 1783790013000,
      "moonriseOnThisDay": null,
      "moonsetOnThisDay": 1783790013000,
      "sunriseOnThisDay": 1783740531000,
      "sunsetOnThisDay": 1783798399000,
      "moonPhase": 7,
      "icon": 2,
      "icon1": null,
      "icon2": null
    }
  ],
  "warnings": [],
  "forecastStart": null,
  "threeHourSummaries": null,
  "fetchedAt": "2026-07-01T22:40:51.939896+00:00"
}